LICENSE
MANIFEST.in
README.rst
setup.py
dpuser/__init__.py
dpuser/apps.py
dpuser/urls.py
dpuser.egg-info/PKG-INFO
dpuser.egg-info/SOURCES.txt
dpuser.egg-info/dependency_links.txt
dpuser.egg-info/requires.txt
dpuser.egg-info/top_level.txt
dpuser/admin/User.py
dpuser/admin/__init__.py
dpuser/managers/BaseUserManager.py
dpuser/managers/UserProfileManager.py
dpuser/managers/__init__.py
dpuser/migrations/0001_initial.py
dpuser/migrations/0002_auto_20170523_1317.py
dpuser/migrations/__init__.py
dpuser/model_bases/AbstractBaseUserProfile.py
dpuser/model_bases/MyAbstractBaseUser.py
dpuser/model_bases/__init__.py
dpuser/models/User.py
dpuser/models/UserProfile.py
dpuser/models/__init__.py
dpuser/serializers/__init__.py
dpuser/serializers/user_detail.py
dpuser/serializers/user_lc.py
dpuser/serializers/user_profile_c.py
dpuser/serializers/user_profile_rud.py
dpuser/serializers/user_rud.py
dpuser/signals/__init__.py
dpuser/signals/handlers.py
dpuser/views/__init__.py
dpuser/views/user_lc.py
dpuser/views/user_rud.py