Metadata-Version: 1.1
Name: dpuser
Version: 0.0.3
Summary: A simple Django app to conduct Web-based polls.
Home-page: https://www.example.com/
Author: Davidpaul Wanjala
Author-email: dp.wanjala@outlook.com
License: BSD License
Platform: UNKNOWN
Classifier: Environment :: Web Environment
Classifier: Framework :: Django
